rx.v
module rx(input clk, input rst, input rx, output reg [7:0] rx_data, output reg rx_done);

parameter CLKS_PER_BIT = 104;

localparam IDLE = 0; //STATES
localparam START = 1;
localparam DATA = 2;
localparam STOP = 3;

reg [1:0] state; //registers
reg [7:0] clk_count;
reg [2:0] bit_index;
reg [7:0] data_reg;

always @(posedge clk or posedge rst) begin
    if(rst) begin
        state<=IDLE;
        clk_count<=0;
        bit_index<=0;
        data_reg<=0;
        rx_data<=0;
        rx_done<=0;
    end

    else begin
        case(state) 
        IDLE: begin
            rx_done<=0;
            clk_count<=0;
            bit_index<=0;

            if(rx==0) begin //start bit detection
                state<=START;
            end
            else begin
                state<=IDLE;
            end
        end
        
        START: begin
            if(clk_count==(CLKS_PER_BIT-1)/2) begin
                clk_count<=0;

                if(rx==0)
                    state<=DATA;
                else 
                    state<=IDLE;
            end
            else begin
                clk_count<=clk_count+1;
                state<=START;
            end
        end

        DATA: begin
            if(clk_count<CLKS_PER_BIT-1) begin
                clk_count<=clk_count+1;
                state<=DATA;
            end

            else begin 
                clk_count<=0;
                data_reg[bit_index]<=rx;

                if(bit_index<7) begin
                    bit_index<=bit_index+1;
                    state<=DATA;
                end

                else begin
                    bit_index<=0;
                    state<=STOP;
                end
            end
        end

        STOP: begin
            if(clk_count<CLKS_PER_BIT-1) begin
                clk_count<=clk_count+1;
                state<=STOP;
            end

            else begin
                rx_data<=data_reg;
                rx_done<=1;
                clk_count<=0;
                state<=IDLE;
            end
    end



        endcase
    end
end

endmodule

tx.v
module tx(input clk, input rst, input tx_start, input [7:0] tx_data, output reg tx);

parameter CLKS_PER_BIT = 104;

localparam IDLE = 0; //STATES
localparam START = 1;
localparam DATA = 2;
localparam STOP = 3;

reg [1:0] state; //registers
reg [7:0] clk_count;
reg [2:0] bit_index;
reg [7:0] data_reg;

always @(posedge clk or posedge rst) begin
    if(rst)begin //RESET
        state<=IDLE;
        tx<=1'b1; //idle=high=1
        clk_count<=0;
        bit_index<=0;
        data_reg<=0;
    end

    else begin
        case(state)
        IDLE: begin
            tx<=1'b1; //keeps high forver
            clk_count<=0;
            bit_index<=0;

            if(tx_start) begin
                data_reg<=tx_data;
                state<=START;
            end
        end

        START: begin
            tx<=1'b0;

            if(clk_count<CLKS_PER_BIT-1)begin
                clk_count<=clk_count+1;
            end    

            else begin   
                clk_count<=0;
                state<=DATA;
            end    
            end
     


        DATA: begin
            tx<=data_reg[bit_index];

            if(clk_count<CLKS_PER_BIT-1)
            begin
                clk_count<=clk_count+1;
            end

            else begin
                clk_count<=0;

                if(bit_index<7)
                begin
                    bit_index<=bit_index+1;
                end

                else begin
                    bit_index<=0;
                    state<=STOP;
                end
            end
        end

        STOP: begin
            tx<=1'b1;
            
            if(clk_count<CLKS_PER_BIT-1) begin
                clk_count<=clk_count+1;
            end

            else begin
                clk_count<=0;
                state<=IDLE;
            end
        end
        endcase

end
end
endmodule

tb_uart.v
module tb_uart;
reg clk;
reg rst;
reg tx_start;
reg [7:0] tx_data;
wire serial_line;
wire [7:0] rx_data;
wire rx_done;

tx transmitter(clk, rst, tx_start, tx_data, serial_line);
rx receiver (clk, rst, serial_line,rx_data, rx_done);

always #5 clk=~clk;

always @(posedge rx_done)
begin
    $display("=================================");
    $display("Time = %0t", $time);
    $display("Received Data = %b", rx_data);
    $display("Received Character = %c", rx_data);
    $display("=================================");
end

always @(serial_line)
begin
    $display("Time=%0t serial_line=%b", $time, serial_line);
end

initial begin
    $dumpfile("uart.vcd");
    $dumpvars(0, tb_uart);

    clk=0; //initialzie
    rst=1;
    tx_data=0;
    tx_start=0;

    #20; //reset release
    rst=0;

    tx_data=8'b01001001;//send data 
    tx_start=1;

    #10;
    tx_start=0;

    #12000;
    $finish;
end
endmodule

uart.vcd
$date
	Sun May 24 13:50:35 2026
$end
$version
	Icarus Verilog
$end
$timescale
	1s
$end
$scope module tb_uart $end
$var wire 1 ! serial_line $end
$var wire 1 " rx_done $end
$var wire 8 # rx_data [7:0] $end
$var reg 1 $ clk $end
$var reg 1 % rst $end
$var reg 8 & tx_data [7:0] $end
$var reg 1 ' tx_start $end
$scope module receiver $end
$var wire 1 $ clk $end
$var wire 1 % rst $end
$var wire 1 ! rx $end
$var parameter 32 ( CLKS_PER_BIT $end
$var parameter 32 ) DATA $end
$var parameter 32 * IDLE $end
$var parameter 32 + START $end
$var parameter 32 , STOP $end
$var reg 3 - bit_index [2:0] $end
$var reg 8 . clk_count [7:0] $end
$var reg 8 / data_reg [7:0] $end
$var reg 8 0 rx_data [7:0] $end
$var reg 1 " rx_done $end
$var reg 2 1 state [1:0] $end
$upscope $end
$scope module transmitter $end
$var wire 1 $ clk $end
$var wire 1 % rst $end
$var wire 8 2 tx_data [7:0] $end
$var wire 1 ' tx_start $end
$var parameter 32 3 CLKS_PER_BIT $end
$var parameter 32 4 DATA $end
$var parameter 32 5 IDLE $end
$var parameter 32 6 START $end
$var parameter 32 7 STOP $end
$var reg 3 8 bit_index [2:0] $end
$var reg 8 9 clk_count [7:0] $end
$var reg 8 : data_reg [7:0] $end
$var reg 2 ; state [1:0] $end
$var reg 1 ! tx $end
$upscope $end
$upscope $end
$enddefinitions $end
$comment Show the parameter values. $end
$dumpall
b11 7
b1 6
b0 5
b10 4
b1101000 3
b11 ,
b1 +
b0 *
b10 )
b1101000 (
$end
#0
$dumpvars
b0 ;
b0 :
b0 9
b0 8
b0 2
b0 1
b0 0
b0 /
b0 .
b0 -
0'
b0 &
1%
0$
b0 #
0"
1!
$end
#5
1$
#10
0$
#15
1$
#20
0$
1'
b1001001 &
b1001001 2
0%
#25
b1 ;
b1001001 :
1$
#30
0$
0'
#35
b1 9
0!
1$
#40
0$
#45
b1 1
b10 9
1$
#50
0$
#55
b11 9
b1 .
1$
#60
0$
#65
b10 .
b100 9
1$
#70
0$
#75
b101 9
b11 .
1$
#80
0$
#85
b100 .
b110 9
1$
#90
0$
#95
b111 9
b101 .
1$
#100
0$
#105
b110 .
b1000 9
1$
#110
0$
#115
b1001 9
b111 .
1$
#120
0$
#125
b1000 .
b1010 9
1$
#130
0$
#135
b1011 9
b1001 .
1$
#140
0$
#145
b1010 .
b1100 9
1$
#150
0$
#155
b1101 9
b1011 .
1$
#160
0$
#165
b1100 .
b1110 9
1$
#170
0$
#175
b1111 9
b1101 .
1$
#180
0$
#185
b1110 .
b10000 9
1$
#190
0$
#195
b10001 9
b1111 .
1$
#200
0$
#205
b10000 .
b10010 9
1$
#210
0$
#215
b10011 9
b10001 .
1$
#220
0$
#225
b10010 .
b10100 9
1$
#230
0$
#235
b10101 9
b10011 .
1$
#240
0$
#245
b10100 .
b10110 9
1$
#250
0$
#255
b10111 9
b10101 .
1$
#260
0$
#265
b10110 .
b11000 9
1$
#270
0$
#275
b11001 9
b10111 .
1$
#280
0$
#285
b11000 .
b11010 9
1$
#290
0$
#295
b11011 9
b11001 .
1$
#300
0$
#305
b11010 .
b11100 9
1$
#310
0$
#315
b11101 9
b11011 .
1$
#320
0$
#325
b11100 .
b11110 9
1$
#330
0$
#335
b11111 9
b11101 .
1$
#340
0$
#345
b11110 .
b100000 9
1$
#350
0$
#355
b100001 9
b11111 .
1$
#360
0$
#365
b100000 .
b100010 9
1$
#370
0$
#375
b100011 9
b100001 .
1$
#380
0$
#385
b100010 .
b100100 9
1$
#390
0$
#395
b100101 9
b100011 .
1$
#400
0$
#405
b100100 .
b100110 9
1$
#410
0$
#415
b100111 9
b100101 .
1$
#420
0$
#425
b100110 .
b101000 9
1$
#430
0$
#435
b101001 9
b100111 .
1$
#440
0$
#445
b101000 .
b101010 9
1$
#450
0$
#455
b101011 9
b101001 .
1$
#460
0$
#465
b101010 .
b101100 9
1$
#470
0$
#475
b101101 9
b101011 .
1$
#480
0$
#485
b101100 .
b101110 9
1$
#490
0$
#495
b101111 9
b101101 .
1$
#500
0$
#505
b101110 .
b110000 9
1$
#510
0$
#515
b110001 9
b101111 .
1$
#520
0$
#525
b110000 .
b110010 9
1$
#530
0$
#535
b110011 9
b110001 .
1$
#540
0$
#545
b110010 .
b110100 9
1$
#550
0$
#555
b110101 9
b110011 .
1$
#560
0$
#565
b10 1
b0 .
b110110 9
1$
#570
0$
#575
b110111 9
b1 .
1$
#580
0$
#585
b10 .
b111000 9
1$
#590
0$
#595
b111001 9
b11 .
1$
#600
0$
#605
b100 .
b111010 9
1$
#610
0$
#615
b111011 9
b101 .
1$
#620
0$
#625
b110 .
b111100 9
1$
#630
0$
#635
b111101 9
b111 .
1$
#640
0$
#645
b1000 .
b111110 9
1$
#650
0$
#655
b111111 9
b1001 .
1$
#660
0$
#665
b1010 .
b1000000 9
1$
#670
0$
#675
b1000001 9
b1011 .
1$
#680
0$
#685
b1100 .
b1000010 9
1$
#690
0$
#695
b1000011 9
b1101 .
1$
#700
0$
#705
b1110 .
b1000100 9
1$
#710
0$
#715
b1000101 9
b1111 .
1$
#720
0$
#725
b10000 .
b1000110 9
1$
#730
0$
#735
b1000111 9
b10001 .
1$
#740
0$
#745
b10010 .
b1001000 9
1$
#750
0$
#755
b1001001 9
b10011 .
1$
#760
0$
#765
b10100 .
b1001010 9
1$
#770
0$
#775
b1001011 9
b10101 .
1$
#780
0$
#785
b10110 .
b1001100 9
1$
#790
0$
#795
b1001101 9
b10111 .
1$
#800
0$
#805
b11000 .
b1001110 9
1$
#810
0$
#815
b1001111 9
b11001 .
1$
#820
0$
#825
b11010 .
b1010000 9
1$
#830
0$
#835
b1010001 9
b11011 .
1$
#840
0$
#845
b11100 .
b1010010 9
1$
#850
0$
#855
b1010011 9
b11101 .
1$
#860
0$
#865
b11110 .
b1010100 9
1$
#870
0$
#875
b1010101 9
b11111 .
1$
#880
0$
#885
b100000 .
b1010110 9
1$
#890
0$
#895
b1010111 9
b100001 .
1$
#900
0$
#905
b100010 .
b1011000 9
1$
#910
0$
#915
b1011001 9
b100011 .
1$
#920
0$
#925
b100100 .
b1011010 9
1$
#930
0$
#935
b1011011 9
b100101 .
1$
#940
0$
#945
b100110 .
b1011100 9
1$
#950
0$
#955
b1011101 9
b100111 .
1$
#960
0$
#965
b101000 .
b1011110 9
1$
#970
0$
#975
b1011111 9
b101001 .
1$
#980
0$
#985
b101010 .
b1100000 9
1$
#990
0$
#995
b1100001 9
b101011 .
1$
#1000
0$
#1005
b101100 .
b1100010 9
1$
#1010
0$
#1015
b1100011 9
b101101 .
1$
#1020
0$
#1025
b101110 .
b1100100 9
1$
#1030
0$
#1035
b1100101 9
b101111 .
1$
#1040
0$
#1045
b110000 .
b1100110 9
1$
#1050
0$
#1055
b1100111 9
b110001 .
1$
#1060
0$
#1065
b110010 .
b10 ;
b0 9
1$
#1070
0$
#1075
b1 9
1!
b110011 .
1$
#1080
0$
#1085
b110100 .
b10 9
1$
#1090
0$
#1095
b11 9
b110101 .
1$
#1100
0$
#1105
b110110 .
b100 9
1$
#1110
0$
#1115
b101 9
b110111 .
1$
#1120
0$
#1125
b111000 .
b110 9
1$
#1130
0$
#1135
b111 9
b111001 .
1$
#1140
0$
#1145
b111010 .
b1000 9
1$
#1150
0$
#1155
b1001 9
b111011 .
1$
#1160
0$
#1165
b111100 .
b1010 9
1$
#1170
0$
#1175
b1011 9
b111101 .
1$
#1180
0$
#1185
b111110 .
b1100 9
1$
#1190
0$
#1195
b1101 9
b111111 .
1$
#1200
0$
#1205
b1000000 .
b1110 9
1$
#1210
0$
#1215
b1111 9
b1000001 .
1$
#1220
0$
#1225
b1000010 .
b10000 9
1$
#1230
0$
#1235
b10001 9
b1000011 .
1$
#1240
0$
#1245
b1000100 .
b10010 9
1$
#1250
0$
#1255
b10011 9
b1000101 .
1$
#1260
0$
#1265
b1000110 .
b10100 9
1$
#1270
0$
#1275
b10101 9
b1000111 .
1$
#1280
0$
#1285
b1001000 .
b10110 9
1$
#1290
0$
#1295
b10111 9
b1001001 .
1$
#1300
0$
#1305
b1001010 .
b11000 9
1$
#1310
0$
#1315
b11001 9
b1001011 .
1$
#1320
0$
#1325
b1001100 .
b11010 9
1$
#1330
0$
#1335
b11011 9
b1001101 .
1$
#1340
0$
#1345
b1001110 .
b11100 9
1$
#1350
0$
#1355
b11101 9
b1001111 .
1$
#1360
0$
#1365
b1010000 .
b11110 9
1$
#1370
0$
#1375
b11111 9
b1010001 .
1$
#1380
0$
#1385
b1010010 .
b100000 9
1$
#1390
0$
#1395
b100001 9
b1010011 .
1$
#1400
0$
#1405
b1010100 .
b100010 9
1$
#1410
0$
#1415
b100011 9
b1010101 .
1$
#1420
0$
#1425
b1010110 .
b100100 9
1$
#1430
0$
#1435
b100101 9
b1010111 .
1$
#1440
0$
#1445
b1011000 .
b100110 9
1$
#1450
0$
#1455
b100111 9
b1011001 .
1$
#1460
0$
#1465
b1011010 .
b101000 9
1$
#1470
0$
#1475
b101001 9
b1011011 .
1$
#1480
0$
#1485
b1011100 .
b101010 9
1$
#1490
0$
#1495
b101011 9
b1011101 .
1$
#1500
0$
#1505
b1011110 .
b101100 9
1$
#1510
0$
#1515
b101101 9
b1011111 .
1$
#1520
0$
#1525
b1100000 .
b101110 9
1$
#1530
0$
#1535
b101111 9
b1100001 .
1$
#1540
0$
#1545
b1100010 .
b110000 9
1$
#1550
0$
#1555
b110001 9
b1100011 .
1$
#1560
0$
#1565
b1100100 .
b110010 9
1$
#1570
0$
#1575
b110011 9
b1100101 .
1$
#1580
0$
#1585
b1100110 .
b110100 9
1$
#1590
0$
#1595
b110101 9
b1100111 .
1$
#1600
0$
#1605
b1 -
b1 /
b0 .
b110110 9
1$
#1610
0$
#1615
b110111 9
b1 .
1$
#1620
0$
#1625
b10 .
b111000 9
1$
#1630
0$
#1635
b111001 9
b11 .
1$
#1640
0$
#1645
b100 .
b111010 9
1$
#1650
0$
#1655
b111011 9
b101 .
1$
#1660
0$
#1665
b110 .
b111100 9
1$
#1670
0$
#1675
b111101 9
b111 .
1$
#1680
0$
#1685
b1000 .
b111110 9
1$
#1690
0$
#1695
b111111 9
b1001 .
1$
#1700
0$
#1705
b1010 .
b1000000 9
1$
#1710
0$
#1715
b1000001 9
b1011 .
1$
#1720
0$
#1725
b1100 .
b1000010 9
1$
#1730
0$
#1735
b1000011 9
b1101 .
1$
#1740
0$
#1745
b1110 .
b1000100 9
1$
#1750
0$
#1755
b1000101 9
b1111 .
1$
#1760
0$
#1765
b10000 .
b1000110 9
1$
#1770
0$
#1775
b1000111 9
b10001 .
1$
#1780
0$
#1785
b10010 .
b1001000 9
1$
#1790
0$
#1795
b1001001 9
b10011 .
1$
#1800
0$
#1805
b10100 .
b1001010 9
1$
#1810
0$
#1815
b1001011 9
b10101 .
1$
#1820
0$
#1825
b10110 .
b1001100 9
1$
#1830
0$
#1835
b1001101 9
b10111 .
1$
#1840
0$
#1845
b11000 .
b1001110 9
1$
#1850
0$
#1855
b1001111 9
b11001 .
1$
#1860
0$
#1865
b11010 .
b1010000 9
1$
#1870
0$
#1875
b1010001 9
b11011 .
1$
#1880
0$
#1885
b11100 .
b1010010 9
1$
#1890
0$
#1895
b1010011 9
b11101 .
1$
#1900
0$
#1905
b11110 .
b1010100 9
1$
#1910
0$
#1915
b1010101 9
b11111 .
1$
#1920
0$
#1925
b100000 .
b1010110 9
1$
#1930
0$
#1935
b1010111 9
b100001 .
1$
#1940
0$
#1945
b100010 .
b1011000 9
1$
#1950
0$
#1955
b1011001 9
b100011 .
1$
#1960
0$
#1965
b100100 .
b1011010 9
1$
#1970
0$
#1975
b1011011 9
b100101 .
1$
#1980
0$
#1985
b100110 .
b1011100 9
1$
#1990
0$
#1995
b1011101 9
b100111 .
1$
#2000
0$
#2005
b101000 .
b1011110 9
1$
#2010
0$
#2015
b1011111 9
b101001 .
1$
#2020
0$
#2025
b101010 .
b1100000 9
1$
#2030
0$
#2035
b1100001 9
b101011 .
1$
#2040
0$
#2045
b101100 .
b1100010 9
1$
#2050
0$
#2055
b1100011 9
b101101 .
1$
#2060
0$
#2065
b101110 .
b1100100 9
1$
#2070
0$
#2075
b1100101 9
b101111 .
1$
#2080
0$
#2085
b110000 .
b1100110 9
1$
#2090
0$
#2095
b1100111 9
b110001 .
1$
#2100
0$
#2105
b110010 .
b1 8
b0 9
1$
#2110
0$
#2115
b1 9
0!
b110011 .
1$
#2120
0$
#2125
b110100 .
b10 9
1$
#2130
0$
#2135
b11 9
b110101 .
1$
#2140
0$
#2145
b110110 .
b100 9
1$
#2150
0$
#2155
b101 9
b110111 .
1$
#2160
0$
#2165
b111000 .
b110 9
1$
#2170
0$
#2175
b111 9
b111001 .
1$
#2180
0$
#2185
b111010 .
b1000 9
1$
#2190
0$
#2195
b1001 9
b111011 .
1$
#2200
0$
#2205
b111100 .
b1010 9
1$
#2210
0$
#2215
b1011 9
b111101 .
1$
#2220
0$
#2225
b111110 .
b1100 9
1$
#2230
0$
#2235
b1101 9
b111111 .
1$
#2240
0$
#2245
b1000000 .
b1110 9
1$
#2250
0$
#2255
b1111 9
b1000001 .
1$
#2260
0$
#2265
b1000010 .
b10000 9
1$
#2270
0$
#2275
b10001 9
b1000011 .
1$
#2280
0$
#2285
b1000100 .
b10010 9
1$
#2290
0$
#2295
b10011 9
b1000101 .
1$
#2300
0$
#2305
b1000110 .
b10100 9
1$
#2310
0$
#2315
b10101 9
b1000111 .
1$
#2320
0$
#2325
b1001000 .
b10110 9
1$
#2330
0$
#2335
b10111 9
b1001001 .
1$
#2340
0$
#2345
b1001010 .
b11000 9
1$
#2350
0$
#2355
b11001 9
b1001011 .
1$
#2360
0$
#2365
b1001100 .
b11010 9
1$
#2370
0$
#2375
b11011 9
b1001101 .
1$
#2380
0$
#2385
b1001110 .
b11100 9
1$
#2390
0$
#2395
b11101 9
b1001111 .
1$
#2400
0$
#2405
b1010000 .
b11110 9
1$
#2410
0$
#2415
b11111 9
b1010001 .
1$
#2420
0$
#2425
b1010010 .
b100000 9
1$
#2430
0$
#2435
b100001 9
b1010011 .
1$
#2440
0$
#2445
b1010100 .
b100010 9
1$
#2450
0$
#2455
b100011 9
b1010101 .
1$
#2460
0$
#2465
b1010110 .
b100100 9
1$
#2470
0$
#2475
b100101 9
b1010111 .
1$
#2480
0$
#2485
b1011000 .
b100110 9
1$
#2490
0$
#2495
b100111 9
b1011001 .
1$
#2500
0$
#2505
b1011010 .
b101000 9
1$
#2510
0$
#2515
b101001 9
b1011011 .
1$
#2520
0$
#2525
b1011100 .
b101010 9
1$
#2530
0$
#2535
b101011 9
b1011101 .
1$
#2540
0$
#2545
b1011110 .
b101100 9
1$
#2550
0$
#2555
b101101 9
b1011111 .
1$
#2560
0$
#2565
b1100000 .
b101110 9
1$
#2570
0$
#2575
b101111 9
b1100001 .
1$
#2580
0$
#2585
b1100010 .
b110000 9
1$
#2590
0$
#2595
b110001 9
b1100011 .
1$
#2600
0$
#2605
b1100100 .
b110010 9
1$
#2610
0$
#2615
b110011 9
b1100101 .
1$
#2620
0$
#2625
b1100110 .
b110100 9
1$
#2630
0$
#2635
b110101 9
b1100111 .
1$
#2640
0$
#2645
b10 -
b0 .
b110110 9
1$
#2650
0$
#2655
b110111 9
b1 .
1$
#2660
0$
#2665
b10 .
b111000 9
1$
#2670
0$
#2675
b111001 9
b11 .
1$
#2680
0$
#2685
b100 .
b111010 9
1$
#2690
0$
#2695
b111011 9
b101 .
1$
#2700
0$
#2705
b110 .
b111100 9
1$
#2710
0$
#2715
b111101 9
b111 .
1$
#2720
0$
#2725
b1000 .
b111110 9
1$
#2730
0$
#2735
b111111 9
b1001 .
1$
#2740
0$
#2745
b1010 .
b1000000 9
1$
#2750
0$
#2755
b1000001 9
b1011 .
1$
#2760
0$
#2765
b1100 .
b1000010 9
1$
#2770
0$
#2775
b1000011 9
b1101 .
1$
#2780
0$
#2785
b1110 .
b1000100 9
1$
#2790
0$
#2795
b1000101 9
b1111 .
1$
#2800
0$
#2805
b10000 .
b1000110 9
1$
#2810
0$
#2815
b1000111 9
b10001 .
1$
#2820
0$
#2825
b10010 .
b1001000 9
1$
#2830
0$
#2835
b1001001 9
b10011 .
1$
#2840
0$
#2845
b10100 .
b1001010 9
1$
#2850
0$
#2855
b1001011 9
b10101 .
1$
#2860
0$
#2865
b10110 .
b1001100 9
1$
#2870
0$
#2875
b1001101 9
b10111 .
1$
#2880
0$
#2885
b11000 .
b1001110 9
1$
#2890
0$
#2895
b1001111 9
b11001 .
1$
#2900
0$
#2905
b11010 .
b1010000 9
1$
#2910
0$
#2915
b1010001 9
b11011 .
1$
#2920
0$
#2925
b11100 .
b1010010 9
1$
#2930
0$
#2935
b1010011 9
b11101 .
1$
#2940
0$
#2945
b11110 .
b1010100 9
1$
#2950
0$
#2955
b1010101 9
b11111 .
1$
#2960
0$
#2965
b100000 .
b1010110 9
1$
#2970
0$
#2975
b1010111 9
b100001 .
1$
#2980
0$
#2985
b100010 .
b1011000 9
1$
#2990
0$
#2995
b1011001 9
b100011 .
1$
#3000
0$
#3005
b100100 .
b1011010 9
1$
#3010
0$
#3015
b1011011 9
b100101 .
1$
#3020
0$
#3025
b100110 .
b1011100 9
1$
#3030
0$
#3035
b1011101 9
b100111 .
1$
#3040
0$
#3045
b101000 .
b1011110 9
1$
#3050
0$
#3055
b1011111 9
b101001 .
1$
#3060
0$
#3065
b101010 .
b1100000 9
1$
#3070
0$
#3075
b1100001 9
b101011 .
1$
#3080
0$
#3085
b101100 .
b1100010 9
1$
#3090
0$
#3095
b1100011 9
b101101 .
1$
#3100
0$
#3105
b101110 .
b1100100 9
1$
#3110
0$
#3115
b1100101 9
b101111 .
1$
#3120
0$
#3125
b110000 .
b1100110 9
1$
#3130
0$
#3135
b1100111 9
b110001 .
1$
#3140
0$
#3145
b110010 .
b10 8
b0 9
1$
#3150
0$
#3155
b1 9
b110011 .
1$
#3160
0$
#3165
b110100 .
b10 9
1$
#3170
0$
#3175
b11 9
b110101 .
1$
#3180
0$
#3185
b110110 .
b100 9
1$
#3190
0$
#3195
b101 9
b110111 .
1$
#3200
0$
#3205
b111000 .
b110 9
1$
#3210
0$
#3215
b111 9
b111001 .
1$
#3220
0$
#3225
b111010 .
b1000 9
1$
#3230
0$
#3235
b1001 9
b111011 .
1$
#3240
0$
#3245
b111100 .
b1010 9
1$
#3250
0$
#3255
b1011 9
b111101 .
1$
#3260
0$
#3265
b111110 .
b1100 9
1$
#3270
0$
#3275
b1101 9
b111111 .
1$
#3280
0$
#3285
b1000000 .
b1110 9
1$
#3290
0$
#3295
b1111 9
b1000001 .
1$
#3300
0$
#3305
b1000010 .
b10000 9
1$
#3310
0$
#3315
b10001 9
b1000011 .
1$
#3320
0$
#3325
b1000100 .
b10010 9
1$
#3330
0$
#3335
b10011 9
b1000101 .
1$
#3340
0$
#3345
b1000110 .
b10100 9
1$
#3350
0$
#3355
b10101 9
b1000111 .
1$
#3360
0$
#3365
b1001000 .
b10110 9
1$
#3370
0$
#3375
b10111 9
b1001001 .
1$
#3380
0$
#3385
b1001010 .
b11000 9
1$
#3390
0$
#3395
b11001 9
b1001011 .
1$
#3400
0$
#3405
b1001100 .
b11010 9
1$
#3410
0$
#3415
b11011 9
b1001101 .
1$
#3420
0$
#3425
b1001110 .
b11100 9
1$
#3430
0$
#3435
b11101 9
b1001111 .
1$
#3440
0$
#3445
b1010000 .
b11110 9
1$
#3450
0$
#3455
b11111 9
b1010001 .
1$
#3460
0$
#3465
b1010010 .
b100000 9
1$
#3470
0$
#3475
b100001 9
b1010011 .
1$
#3480
0$
#3485
b1010100 .
b100010 9
1$
#3490
0$
#3495
b100011 9
b1010101 .
1$
#3500
0$
#3505
b1010110 .
b100100 9
1$
#3510
0$
#3515
b100101 9
b1010111 .
1$
#3520
0$
#3525
b1011000 .
b100110 9
1$
#3530
0$
#3535
b100111 9
b1011001 .
1$
#3540
0$
#3545
b1011010 .
b101000 9
1$
#3550
0$
#3555
b101001 9
b1011011 .
1$
#3560
0$
#3565
b1011100 .
b101010 9
1$
#3570
0$
#3575
b101011 9
b1011101 .
1$
#3580
0$
#3585
b1011110 .
b101100 9
1$
#3590
0$
#3595
b101101 9
b1011111 .
1$
#3600
0$
#3605
b1100000 .
b101110 9
1$
#3610
0$
#3615
b101111 9
b1100001 .
1$
#3620
0$
#3625
b1100010 .
b110000 9
1$
#3630
0$
#3635
b110001 9
b1100011 .
1$
#3640
0$
#3645
b1100100 .
b110010 9
1$
#3650
0$
#3655
b110011 9
b1100101 .
1$
#3660
0$
#3665
b1100110 .
b110100 9
1$
#3670
0$
#3675
b110101 9
b1100111 .
1$
#3680
0$
#3685
b11 -
b0 .
b110110 9
1$
#3690
0$
#3695
b110111 9
b1 .
1$
#3700
0$
#3705
b10 .
b111000 9
1$
#3710
0$
#3715
b111001 9
b11 .
1$
#3720
0$
#3725
b100 .
b111010 9
1$
#3730
0$
#3735
b111011 9
b101 .
1$
#3740
0$
#3745
b110 .
b111100 9
1$
#3750
0$
#3755
b111101 9
b111 .
1$
#3760
0$
#3765
b1000 .
b111110 9
1$
#3770
0$
#3775
b111111 9
b1001 .
1$
#3780
0$
#3785
b1010 .
b1000000 9
1$
#3790
0$
#3795
b1000001 9
b1011 .
1$
#3800
0$
#3805
b1100 .
b1000010 9
1$
#3810
0$
#3815
b1000011 9
b1101 .
1$
#3820
0$
#3825
b1110 .
b1000100 9
1$
#3830
0$
#3835
b1000101 9
b1111 .
1$
#3840
0$
#3845
b10000 .
b1000110 9
1$
#3850
0$
#3855
b1000111 9
b10001 .
1$
#3860
0$
#3865
b10010 .
b1001000 9
1$
#3870
0$
#3875
b1001001 9
b10011 .
1$
#3880
0$
#3885
b10100 .
b1001010 9
1$
#3890
0$
#3895
b1001011 9
b10101 .
1$
#3900
0$
#3905
b10110 .
b1001100 9
1$
#3910
0$
#3915
b1001101 9
b10111 .
1$
#3920
0$
#3925
b11000 .
b1001110 9
1$
#3930
0$
#3935
b1001111 9
b11001 .
1$
#3940
0$
#3945
b11010 .
b1010000 9
1$
#3950
0$
#3955
b1010001 9
b11011 .
1$
#3960
0$
#3965
b11100 .
b1010010 9
1$
#3970
0$
#3975
b1010011 9
b11101 .
1$
#3980
0$
#3985
b11110 .
b1010100 9
1$
#3990
0$
#3995
b1010101 9
b11111 .
1$
#4000
0$
#4005
b100000 .
b1010110 9
1$
#4010
0$
#4015
b1010111 9
b100001 .
1$
#4020
0$
#4025
b100010 .
b1011000 9
1$
#4030
0$
#4035
b1011001 9
b100011 .
1$
#4040
0$
#4045
b100100 .
b1011010 9
1$
#4050
0$
#4055
b1011011 9
b100101 .
1$
#4060
0$
#4065
b100110 .
b1011100 9
1$
#4070
0$
#4075
b1011101 9
b100111 .
1$
#4080
0$
#4085
b101000 .
b1011110 9
1$
#4090
0$
#4095
b1011111 9
b101001 .
1$
#4100
0$
#4105
b101010 .
b1100000 9
1$
#4110
0$
#4115
b1100001 9
b101011 .
1$
#4120
0$
#4125
b101100 .
b1100010 9
1$
#4130
0$
#4135
b1100011 9
b101101 .
1$
#4140
0$
#4145
b101110 .
b1100100 9
1$
#4150
0$
#4155
b1100101 9
b101111 .
1$
#4160
0$
#4165
b110000 .
b1100110 9
1$
#4170
0$
#4175
b1100111 9
b110001 .
1$
#4180
0$
#4185
b110010 .
b11 8
b0 9
1$
#4190
0$
#4195
b1 9
1!
b110011 .
1$
#4200
0$
#4205
b110100 .
b10 9
1$
#4210
0$
#4215
b11 9
b110101 .
1$
#4220
0$
#4225
b110110 .
b100 9
1$
#4230
0$
#4235
b101 9
b110111 .
1$
#4240
0$
#4245
b111000 .
b110 9
1$
#4250
0$
#4255
b111 9
b111001 .
1$
#4260
0$
#4265
b111010 .
b1000 9
1$
#4270
0$
#4275
b1001 9
b111011 .
1$
#4280
0$
#4285
b111100 .
b1010 9
1$
#4290
0$
#4295
b1011 9
b111101 .
1$
#4300
0$
#4305
b111110 .
b1100 9
1$
#4310
0$
#4315
b1101 9
b111111 .
1$
#4320
0$
#4325
b1000000 .
b1110 9
1$
#4330
0$
#4335
b1111 9
b1000001 .
1$
#4340
0$
#4345
b1000010 .
b10000 9
1$
#4350
0$
#4355
b10001 9
b1000011 .
1$
#4360
0$
#4365
b1000100 .
b10010 9
1$
#4370
0$
#4375
b10011 9
b1000101 .
1$
#4380
0$
#4385
b1000110 .
b10100 9
1$
#4390
0$
#4395
b10101 9
b1000111 .
1$
#4400
0$
#4405
b1001000 .
b10110 9
1$
#4410
0$
#4415
b10111 9
b1001001 .
1$
#4420
0$
#4425
b1001010 .
b11000 9
1$
#4430
0$
#4435
b11001 9
b1001011 .
1$
#4440
0$
#4445
b1001100 .
b11010 9
1$
#4450
0$
#4455
b11011 9
b1001101 .
1$
#4460
0$
#4465
b1001110 .
b11100 9
1$
#4470
0$
#4475
b11101 9
b1001111 .
1$
#4480
0$
#4485
b1010000 .
b11110 9
1$
#4490
0$
#4495
b11111 9
b1010001 .
1$
#4500
0$
#4505
b1010010 .
b100000 9
1$
#4510
0$
#4515
b100001 9
b1010011 .
1$
#4520
0$
#4525
b1010100 .
b100010 9
1$
#4530
0$
#4535
b100011 9
b1010101 .
1$
#4540
0$
#4545
b1010110 .
b100100 9
1$
#4550
0$
#4555
b100101 9
b1010111 .
1$
#4560
0$
#4565
b1011000 .
b100110 9
1$
#4570
0$
#4575
b100111 9
b1011001 .
1$
#4580
0$
#4585
b1011010 .
b101000 9
1$
#4590
0$
#4595
b101001 9
b1011011 .
1$
#4600
0$
#4605
b1011100 .
b101010 9
1$
#4610
0$
#4615
b101011 9
b1011101 .
1$
#4620
0$
#4625
b1011110 .
b101100 9
1$
#4630
0$
#4635
b101101 9
b1011111 .
1$
#4640
0$
#4645
b1100000 .
b101110 9
1$
#4650
0$
#4655
b101111 9
b1100001 .
1$
#4660
0$
